odoo/addons/rental_pricelist/README.rst
odoo/addons/rental_pricelist/__init__.py
odoo/addons/rental_pricelist/__manifest__.py
odoo/addons/rental_pricelist/hooks.py
odoo/addons/rental_pricelist/README/CONFIGURATION.rst
odoo/addons/rental_pricelist/README/CONTRIBUTORS.rst
odoo/addons/rental_pricelist/README/DESCRIPTION.rst
odoo/addons/rental_pricelist/README/HISTORY.rst
odoo/addons/rental_pricelist/README/USAGE.rst
odoo/addons/rental_pricelist/i18n/de.po
odoo/addons/rental_pricelist/i18n/rental_pricelist.pot
odoo/addons/rental_pricelist/models/__init__.py
odoo/addons/rental_pricelist/models/product.py
odoo/addons/rental_pricelist/models/product_pricelist_item.py
odoo/addons/rental_pricelist/models/res_company.py
odoo/addons/rental_pricelist/models/sale.py
odoo/addons/rental_pricelist/static/description/icon.png
odoo/addons/rental_pricelist/static/description/index.html
odoo/addons/rental_pricelist/tests/__init__.py
odoo/addons/rental_pricelist/tests/test_rental_pricelist.py
odoo/addons/rental_pricelist/views/product_view.xml
odoo/addons/rental_pricelist/views/res_company_view.xml
odoo/addons/rental_pricelist/views/sale_view.xml
odoo14_addon_rental_pricelist-14.0.1.0.2.dist-info/METADATA
odoo14_addon_rental_pricelist-14.0.1.0.2.dist-info/WHEEL
odoo14_addon_rental_pricelist-14.0.1.0.2.dist-info/top_level.txt
odoo14_addon_rental_pricelist-14.0.1.0.2.dist-info/RECORD
